metaai/__init__.py
metaai/version.py
metaai-0.0.0.dist-info/METADATA
metaai-0.0.0.dist-info/WHEEL
metaai-0.0.0.dist-info/top_level.txt
metaai-0.0.0.dist-info/RECORD
