Metadata-Version: 2.1
Name: metaai
Version: 0.0.0
Summary: Library of Meta Learning
Home-page: http://pypi.org/project/metaai
License: UNKNOWN
Platform: UNKNOWN
Classifier: Programming Language :: Python
Classifier: Intended Audience :: Science/Research
